{"/":{"bundle.9cd0c.css":{"type":"style","weight":1},"bundle.a815a.esm.js":{"type":"script","weight":1},"route-home.chunk.dfe3e.esm.js":{"type":"script","weight":0.9}},"/dogs":{"bundle.9cd0c.css":{"type":"style","weight":1},"bundle.a815a.esm.js":{"type":"script","weight":1},"route-dogs.chunk.eec4b.esm.js":{"type":"script","weight":0.9}},"/logout":{"bundle.9cd0c.css":{"type":"style","weight":1},"bundle.a815a.esm.js":{"type":"script","weight":1},"route-logout.chunk.e815e.esm.js":{"type":"script","weight":0.9}},"/search":{"bundle.9cd0c.css":{"type":"style","weight":1},"bundle.a815a.esm.js":{"type":"script","weight":1},"route-search.chunk.bcc13.esm.js":{"type":"script","weight":0.9}},"/teams":{"bundle.9cd0c.css":{"type":"style","weight":1},"bundle.a815a.esm.js":{"type":"script","weight":1},"route-teams.chunk.34449.esm.js":{"type":"script","weight":0.9}},"/tracks":{"bundle.9cd0c.css":{"type":"style","weight":1},"bundle.a815a.esm.js":{"type":"script","weight":1},"route-tracks.chunk.8b722.esm.js":{"type":"script","weight":0.9}},"/users":{"bundle.9cd0c.css":{"type":"style","weight":1},"bundle.a815a.esm.js":{"type":"script","weight":1},"route-users.chunk.e61d9.esm.js":{"type":"script","weight":0.9}},"/workouts":{"bundle.9cd0c.css":{"type":"style","weight":1},"bundle.a815a.esm.js":{"type":"script","weight":1},"route-workouts.chunk.061a7.esm.js":{"type":"script","weight":0.9}}}